{"guide_caveats.md":"DGCA0L6n","composables_useboostercomponentobserver.md":"Ch_WaOzu","components_booster-picture.md":"DgjShVm3","components_booster-vimeo.md":"CPeUV2aw","components_weak-hardware-overlay.md":"y0ESMI-I","composables_useboostercritical.md":"2PQGutaI","v2_components_booster-layer.md":"y3rgLava","guide_setup.md":"BJZjC7V_","v2_guide_usage.md":"BcYhV3X4","guide_options.md":"tt2bD4Z_","v2_directives_v-font.md":"F0PqB4Kv","migration_v2-0-13.md":"vkuz9-tP","components_booster-layer.md":"BkEwUqbU","directives_v-font.md":"DYVUzaFN","migration_v2.md":"DZ9CMeME","v2_guide_caveats.md":"3dJoMkxM","components_booster-image.md":"Dug0dpSD","v2_components_booster-picture.md":"DZz8_KCX","composables_useboosterfont.md":"B66YqCB0","v2_guide_options.md":"4oh088F2","composables_useboosterhead.md":"MdOqzkwI","v2_concept.md":"BUlGfxC0","v2_components_booster-iframe.md":"OEQYLzs_","components_booster-iframe.md":"BEsyxF6i","components_booster-youtube.md":"Bq8wIumf","guide_usage.md":"CXmGApw4","concept.md":"D-TOuu-G","composables_useboosterconfig.md":"DX0CkR4U","v2_guide_setup.md":"Cu9Rc2g5","index.md":"DYFnEwZD","v2_components_booster-youtube.md":"y5Se7UIC","v2_classes_loading-spinner.md":"CX4Zrt-8","v2_components_booster-vimeo.md":"VKR3GbTK","migration_v2-2-0.md":"DA2DFpR3","v2_components_booster-image.md":"BmzHFMeW","v2_index.md":"BgDNGSR7","migration_v3.md":"CXsI-nSl"}
