{"id":"e2800960-3da1-4736-a928-84792490dce8","timestamp":1743169839009,"matcher":{"static":{},"wildcard":{},"dynamic":{}},"prerendered":["/","/tests","/tests/iframe","/tests/v-font-media","/tests/v-font","/tests/youtube","/tests/picture","/tests/vimeo","/tests/v-font-scroll","/tests/image","/tests/useBoosterHead/1","/tests/useBoosterHead","/tests/useBoosterHead/2","/tests/useBoosterHead/empty-1","/tests/useBoosterHead/empty-2","/tests/weak-hardware-overlay","/tests/booster-layer","/tests/booster-loader","/tests/booster-hydrate"]}